Workbook
Name aporte: Planilha1!$D$18
Name patrimonio: Planilha1!$D$21
Name qtd_anos: Planilha1!$D$19
Name rendimento_da_carteira: Planilha1!$D$14
Name taxa_mensal: Planilha1!$D$20

Sheet Planilha1
B12: CONFIGURAÇOES
B13: Salario | D13: 4200
B14: Rendimento da Carteira | D14: 0.006
B15: Sugestao de investimento (30%) | D15: =D13*30% -> 1260
B17: INVESTIMENTO MENSAL
B18: Quanto investir por mês | D18: 1260
B19: Por quantos anos | D19: 10
B20: Taxa de rendimento mensal | D20: 0.01079
B21: Patrimônio acumulado | D21: =FV(taxa_mensal,qtd_anos*12,aporte*-1) -> 306538.11
B22: Dividendos mensais | D22: =patrimonio*rendimento_da_carteira -> 1839.2286
B24: CENÁRIOS | D24: Dividendo
A25: 2 | B25: Quanto em 2 anos ? | C25: =FV($D$20,$A25*12,$D$18*-1) -> 34306.81 | D25: =C25*rendimento_da_carteira -> 205.84086
A26: 5 | B26: Quanto em 5 anos ? | C26: =FV($D$20,$A26*12,$D$18*-1) -> 105558.91 | D26: =C26*rendimento_da_carteira -> 633.35347
A27: 10 | B27: Quanto em 10 anos ? | C27: =FV($D$20,$A27*12,$D$18*-1) -> 306538.11 | D27: =C27*rendimento_da_carteira -> 1839.2286
A28: 20 | B28: Quanto em 20 anos ? | C28: =FV($D$20,$A28*12,$D$18*-1) -> 1417750 | D28: =C28*rendimento_da_carteira -> 8506.4999
A29: 30 | B29: Quanto em 30 anos ? | C29: =FV($D$20,$A29*12,$D$18*-1) -> 5445933.8 | D29: =C29*rendimento_da_carteira -> 32675.603
B32: PERFIL | C32: Agressivo
B33: VALOR A SER INVESTIDO POR MÊS | C33: =D15 -> 1260
B36: TIPO DE FII | C36: Percentual Sugerido | D36: Valores
B37: PAPEL | C37: =VLOOKUP($C$32&"-"&B37,Planilha2!$B:$E,4,FALSE) -> 0.5 | D37: =C37*$C$33 -> 630
B38: TIJOLO | C38: =VLOOKUP($C$32&"-"&B38,Planilha2!$B$1:$E$20,4,FALSE) -> 0.1 | D38: =C38*$C$33 -> 126
B39: HIBRIDOS | C39: =VLOOKUP($C$32&"-"&B39,Planilha2!$B$1:$E$20,4,FALSE) -> 0.05 | D39: =C39*$C$33 -> 63
B40: FOFs | C40: =VLOOKUP($C$32&"-"&B40,Planilha2!$B$1:$E$20,4,FALSE) -> 0.05 | D40: =C40*$C$33 -> 63
B41: DESENVOLVIMENTO | C41: =VLOOKUP($C$32&"-"&B41,Planilha2!$B$1:$E$20,4,FALSE) -> 0.2 | D41: =C41*$C$33 -> 252
B42: HOTELARIAS | C42: =VLOOKUP($C$32&"-"&B42,Planilha2!$B$1:$E$20,4,FALSE) -> 0.1 | D42: =C42*$C$33 -> 126
D43: =SUM(D37:D42) -> 1260

Sheet Planilha2
B2: CHAVE | C2: PERFIL | D2: TIPO DE FII | E2: %
B3: =$C$3&"-"&D3 -> Conservador-PAPEL | C3: Conservador | D3: PAPEL | E3: 0.3
B4: =$C$3&"-"&D4 -> Conservador-TIJOLO | C4: Conservador | D4: TIJOLO | E4: 0.5
B5: =$C$3&"-"&D5 -> Conservador-HIBRIDOS | C5: Conservador | D5: HIBRIDOS | E5: 0.1
B6: =$C$3&"-"&D6 -> Conservador-FOFs | C6: Conservador | D6: FOFs | E6: 0.1
B7: =$C$3&"-"&D7 -> Conservador-DESENVOLVIMENTO | C7: Conservador | D7: DESENVOLVIMENTO | E7: 0
B8: =$C$3&"-"&D8 -> Conservador-HOTELARIAS | C8: Conservador | D8: HOTELARIAS | E8: 0
B9: Moderado-PAPEL | C9: Moderado | D9: PAPEL | E9: 0.32
B10: Moderado-TIJOLO | C10: Moderado | D10: TIJOLO | E10: 0.3
B11: Moderado-HIBRIDOS | C11: Moderado | D11: HIBRIDOS | E11: 0.08
B12: Moderado-FOFs | C12: Moderado | D12: FOFs | E12: 0.1
B13: Moderado-DESENVOLVIMENTO | C13: Moderado | D13: DESENVOLVIMENTO | E13: 0.1
B14: Moderado-HOTELARIAS | C14: Moderado | D14: HOTELARIAS | E14: 0.1
B15: Agressivo-PAPEL | C15: Agressivo | D15: PAPEL | E15: 0.5
B16: Agressivo-TIJOLO | C16: Agressivo | D16: TIJOLO | E16: 0.1
B17: Agressivo-HIBRIDOS | C17: Agressivo | D17: HIBRIDOS | E17: 0.05
B18: Agressivo-FOFs | C18: Agressivo | D18: FOFs | E18: 0.05
B19: Agressivo-DESENVOLVIMENTO | C19: Agressivo | D19: DESENVOLVIMENTO | E19: 0.2
B20: Agressivo-HOTELARIAS | C20: Agressivo | D20: HOTELARIAS | E20: 0.1
